{
    "android": {
        "UnityAds": {
            "gameId": "1493045", 
            "testMode": true
        }, 
        "Review": {
            "LaunchLimit": 3, 
            "DayForReminding": 1, 
            "tryPromptWhenInit": true, 
            "DayLimit": 0, 
            "LaunchForReminding": 2, 
            "UserEventLimit": 0
        }, 
        "Share": {
            "platforms": {
                "Facebook": {}, 
                "Twitter": {
                    "params": {
                        "secret": "nlmUdPNcFGLWhyLu9cD794EDuDrVQnjd0YjTpB6sX8oHIQRrne", 
                        "key": "EuovpLL0UhSGB7Jv5eKFJNMqO"
                    }
                }, 
                "SMS": {}, 
                "Mail": {}
            }
        }, 
        "AdMob": {
            "test": false, 
            "ads": {
                "gameover": {
                    "type": "interstitial", 
                    "id": "ca-app-pub-1329374026572143/1092476511"
                }, 
                "home": {
                    "width": 320, 
                    "type": "banner", 
                    "id": "ca-app-pub-1329374026572143/2685130917", 
                    "alignment": "bottom", 
                    "height": 50
                }, 
                "next_level": {
                    "type": "interstitial", 
                    "id": "ca-app-pub-1329374026572143/4564434111"
                }, 
                "top_banner": {
                    "type": "banner", 
                    "id": "ca-app-pub-1329374026572143/3087700911", 
                    "alignment": "top"
                }, 
                "rewarded": {
                    "type": "rewarded_video", 
                    "id": "ca-app-pub-1329374026572143/8251968111"
                }
            }
        }, 
        "Facebook": {
            "debug": false
        }, 
        "AdColony": {
            "debug": true, 
            "id": "app185a7e71e1714831a49ec7", 
            "ads": {
                "v4vc": {
                    "v4vc": true, 
                    "pre_popup": true, 
                    "zone": "vz1fd5a8b2bf6841a0a4b826", 
                    "post_popup": true
                }, 
                "video": {
                    "v4vc": false, 
                    "zone": "vz06e8c32a037749699e7050"
                }
            }
        }
    }, 
    "ios": {
        "UnityAds": {
            "gameId": "1493044", 
            "testMode": true
        }, 
        "Review": {
            "LaunchLimit": 3, 
            "DayForReminding": 1, 
            "tryPromptWhenInit": true, 
            "AppID": "587767923", 
            "DayLimit": 0, 
            "LaunchForReminding": 2, 
            "UserEventLimit": 0
        }, 
        "Share": {
            "platforms": {
                "Facebook": {}, 
                "Twitter": {
                    "params": {
                        "secret": "haVcKarM96Sr4390XLQoHjyRUSyuHdkMX6letcc38h8TOWyiR9", 
                        "key": "BUJTV6NEM7BAhhm82B12VbKGy"
                    }
                }, 
                "SMS": {}, 
                "Mail": {}
            }
        }, 
        "AdMob": {
            "test": false, 
            "safearea": true, 
            "ads": {
                "gameover": {
                    "type": "interstitial", 
                    "id": "ca-app-pub-1329374026572143/4185543717"
                }, 
                "home": {
                    "width": 320, 
                    "type": "banner", 
                    "id": "ca-app-pub-1329374026572143/3847466511", 
                    "alignment": "bottom", 
                    "height": 50
                }, 
                "next_level": {
                    "type": "interstitial", 
                    "id": "ca-app-pub-1329374026572143/9390403312"
                }, 
                "top_banner": {
                    "type": "banner", 
                    "id": "ca-app-pub-1329374026572143/6690628914", 
                    "alignment": "top"
                }, 
                "rewarded": {
                    "type": "rewarded_video", 
                    "id": "ca-app-pub-1329374026572143/7991602916"
                }
            }
        }, 
        "Facebook": {
            "debug": true
        }, 
        "AdColony": {
            "debug": true, 
            "id": "appbdee68ae27024084bb334a", 
            "ads": {
                "v4vc": {
                    "v4vc": true, 
                    "pre_popup": true, 
                    "zone": "vzf8e4e97704c4445c87504e", 
                    "post_popup": true
                }, 
                "video": {
                    "v4vc": false, 
                    "zone": "vzf8fb4670a60e4a139d01b5"
                }
            }
        }
    }, 
    "amazon": {
        "Review": {
            "LaunchLimit": 3, 
            "DayForReminding": 1, 
            "market": "amazon", 
            "tryPromptWhenInit": true, 
            "DayLimit": 0, 
            "LaunchForReminding": 2, 
            "UserEventLimit": 0
        }
    }
}